cloudbase_agent/__init__.py
cloudbase_agent/long_term_memory/__init__.py
cloudbase_agent/long_term_memory/long_term_memory_base.py
cloudbase_agent/long_term_memory/mem0_long_term_memory.py
cloudbase_agent/long_term_memory/tdai_long_term_memory.py
cloudbase_agent/memory/__init__.py
cloudbase_agent/memory/in_memory_memory.py
cloudbase_agent/memory/memory_base.py
cloudbase_agent/memory/tdai_memory.py
cloudbase_agent/tdaimemory/.gitignore
cloudbase_agent/tdaimemory/.python-version
cloudbase_agent/tdaimemory/CHANGELOG.md
cloudbase_agent/tdaimemory/LICENSE
cloudbase_agent/tdaimemory/README.md
cloudbase_agent/tdaimemory/__init__.py
cloudbase_agent/tdaimemory/pyproject.toml
cloudbase_agent/tdaimemory/uv.lock
cloudbase_agent/tdaimemory/examples/example.py
cloudbase_agent/tdaimemory/examples/quick_start.py
cloudbase_agent/tdaimemory/tdaimemory/__init__.py
cloudbase_agent/tdaimemory/tdaimemory/client.py
cloudbase_agent/tdaimemory/tdaimemory/errors.py
cloudbase_agent/tdaimemory/tdaimemory/params.py
cloudbase_agent/tdaimemory/tdaimemory/stub/__init__.py
cloudbase_agent/tdaimemory/tdaimemory/stub/stub.py
cloudbase_agent/tdaimemory/tests/__init__.py
cloudbase_agent/utils/__init__.py
cloudbase_agent/utils/token_utils.py
cloudbase_agent_storage-0.1.10.dist-info/METADATA
cloudbase_agent_storage-0.1.10.dist-info/WHEEL
cloudbase_agent_storage-0.1.10.dist-info/RECORD
